docs/__init__.py
docs/conf.py
fired_up/__init__.py
tests/__init__.py
tests/conftest.py
tests/test_bug.py
tests/test_command_line.py
tests/test_function_commands.py
tests/test_hello.py
tests/test_hierarchy.py
tests/test_invalid_items.py
tests/test_results.py
tests/test_tuple_handler.py
fired_up-0.1.0.dist-info/LICENSE.txt
fired_up-0.1.0.dist-info/METADATA
fired_up-0.1.0.dist-info/WHEEL
fired_up-0.1.0.dist-info/top_level.txt
fired_up-0.1.0.dist-info/RECORD
