Metadata-Version: 2.1
Name: fired-up
Version: 0.1.0
Summary: conventions and supporting tools for using Fire in a more natural-ish language style
Home-page: https://github.com/christophevg/fired-up
Author: Christophe VG
License: MIT
Keywords: python fire DSL
Platform: UNKNOWN
Classifier: Development Status :: 4 - Beta
Classifier: Intended Audience :: Developers
Classifier: Programming Language :: Python :: 3
Classifier: Programming Language :: Python :: 3.8
Classifier: Programming Language :: Python :: 3.9
Classifier: Programming Language :: Python :: 3.10
Classifier: Programming Language :: Python :: 3.11
Requires-Dist: fire ==0.5.0
